[{"Name": "Dish", "Confidence": 99.99650573730469, "Instances": [], "Parents": [{"Name": "Meal"}, {"Name": "Food"}]}, {"Name": "Meal", "Confidence": 99.99650573730469, "Instances": [], "Parents": [{"Name": "Food"}]}, {"Name": "Food", "Confidence": 99.99650573730469, "Instances": [], "Parents": []}, {"Name": "Bowl", "Confidence": 99.98636627197266, "Instances": [], "Parents": []}, {"Name": "Soup Bowl", "Confidence": 94.00224304199219, "Instances": [], "Parents": [{"Name": "Bowl"}]}, {"Name": "Soup", "Confidence": 89.51396942138672, "Instances": [], "Parents": [{"Name": "Dish"}, {"Name": "Soup Bowl"}, {"Name": "Meal"}, {"Name": "Bowl"}, {"Name": "Food"}]}, {"Name": "Noodle", "Confidence": 87.01708221435547, "Instances": [], "Parents": [{"Name": "Pasta"}, {"Name": "Food"}]}, {"Name": "Pasta", "Confidence": 87.01708221435547, "Instances": [], "Parents": [{"Name": "Food"}]}]