[{"Name": "Waffle", "Confidence": 99.32174682617188, "Instances": [], "Parents": [{"Name": "Food"}]}, {"Name": "Food", "Confidence": 99.32174682617188, "Instances": [], "Parents": []}, {"Name": "Bread", "Confidence": 88.54097747802734, "Instances": [{"BoundingBox": {"Width": 0.9778737425804138, "Height": 0.376508891582489, "Left": 0.021200334653258324, "Top": 0.6227504014968872}, "Confidence": 88.54097747802734}, {"BoundingBox": {"Width": 0.38819512724876404, "Height": 0.2848980128765106, "Left": 0.4805712103843689, "Top": 0.34460359811782837}, "Confidence": 74.2968521118164}], "Parents": [{"Name": "Food"}]}, {"Name": "Ice Cream", "Confidence": 87.14653015136719, "Instances": [{"BoundingBox": {"Width": 0.5105705261230469, "Height": 0.337794691324234, "Left": 0.02032233402132988, "Top": 0.3675568401813507}, "Confidence": 87.14653015136719}], "Parents": [{"Name": "Cream"}, {"Name": "Dessert"}, {"Name": "Food"}]}, {"Name": "Dessert", "Confidence": 87.14653015136719, "Instances": [], "Parents": [{"Name": "Food"}]}, {"Name": "Cream", "Confidence": 87.14653015136719, "Instances": [], "Parents": [{"Name": "Dessert"}, {"Name": "Food"}]}, {"Name": "Creme", "Confidence": 87.14653015136719, "Instances": [], "Parents": [{"Name": "Dessert"}, {"Name": "Food"}]}]