[{"Name": "Sweets", "Confidence": 99.7945785522461, "Instances": [], "Parents": [{"Name": "Food"}]}, {"Name": "Confectionery", "Confidence": 99.7945785522461, "Instances": [], "Parents": [{"Name": "Food"}]}, {"Name": "Food", "Confidence": 99.7945785522461, "Instances": [], "Parents": []}, {"Name": "Person", "Confidence": 96.06480407714844, "Instances": [{"BoundingBox": {"Width": 0.396903395652771, "Height": 0.49338024854660034, "Left": 0.012440957129001617, "Top": 0.49558648467063904}, "Confidence": 96.06480407714844}], "Parents": []}, {"Name": "Human", "Confidence": 96.06480407714844, "Instances": [], "Parents": []}, {"Name": "Bread", "Confidence": 90.12356567382812, "Instances": [], "Parents": [{"Name": "Food"}]}]