[{"Name": "Landscape", "Confidence": 99.98941040039062, "Instances": [], "Parents": [{"Name": "Outdoors"}, {"Name": "Nature"}]}, {"Name": "Nature", "Confidence": 99.98941040039062, "Instances": [], "Parents": []}, {"Name": "Outdoors", "Confidence": 99.98941040039062, "Instances": [], "Parents": []}, {"Name": "Scenery", "Confidence": 99.97850036621094, "Instances": [], "Parents": [{"Name": "Outdoors"}, {"Name": "Nature"}]}, {"Name": "Aerial View", "Confidence": 99.25564575195312, "Instances": [], "Parents": [{"Name": "Landscape"}, {"Name": "Scenery"}, {"Name": "Outdoors"}, {"Name": "Nature"}]}, {"Name": "Road", "Confidence": 96.96507263183594, "Instances": [], "Parents": []}, {"Name": "Intersection", "Confidence": 90.67929077148438, "Instances": [], "Parents": [{"Name": "Road"}]}, {"Name": "City", "Confidence": 89.88665008544922, "Instances": [], "Parents": [{"Name": "Urban"}, {"Name": "Building"}]}, {"Name": "Urban", "Confidence": 89.88665008544922, "Instances": [], "Parents": []}, {"Name": "Building", "Confidence": 89.88665008544922, "Instances": [], "Parents": []}]