[{"Name": "Face", "Confidence": 99.2083969116211, "Instances": [], "Parents": [{"Name": "Person"}]}, {"Name": "Person", "Confidence": 99.2083969116211, "Instances": [{"BoundingBox": {"Width": 0.9868579506874084, "Height": 0.9563426375389099, "Left": 0.012447611428797245, "Top": 0.011356404982507229}, "Confidence": 97.66756439208984}], "Parents": []}, {"Name": "Human", "Confidence": 99.2083969116211, "Instances": [], "Parents": []}, {"Name": "Mouth", "Confidence": 85.40909576416016, "Instances": [], "Parents": []}, {"Name": "Lip", "Confidence": 85.40909576416016, "Instances": [], "Parents": []}, {"Name": "Clothing", "Confidence": 81.87688446044922, "Instances": [], "Parents": []}, {"Name": "Apparel", "Confidence": 81.87688446044922, "Instances": [], "Parents": []}]