[{"Name": "Leaf", "Confidence": 99.93083953857422, "Instances": [], "Parents": [{"Name": "Plant"}]}, {"Name": "Plant", "Confidence": 99.93083953857422, "Instances": [], "Parents": []}, {"Name": "Person", "Confidence": 95.09180450439453, "Instances": [{"BoundingBox": {"Width": 0.4951341152191162, "Height": 0.37855833768844604, "Left": 0.02271144650876522, "Top": 0.6084287166595459}, "Confidence": 95.09180450439453}], "Parents": []}, {"Name": "Human", "Confidence": 95.09180450439453, "Instances": [], "Parents": []}, {"Name": "Droplet", "Confidence": 89.39891815185547, "Instances": [], "Parents": []}]