[{"Name": "Clothing", "Confidence": 99.9864501953125, "Instances": [], "Parents": []}, {"Name": "Evening Dress", "Confidence": 99.24073791503906, "Instances": [], "Parents": [{"Name": "Robe"}, {"Name": "Gown"}, {"Name": "Fashion"}, {"Name": "Clothing"}]}, {"Name": "Robe", "Confidence": 99.24073791503906, "Instances": [], "Parents": [{"Name": "Fashion"}, {"Name": "Clothing"}]}, {"Name": "Gown", "Confidence": 99.24073791503906, "Instances": [], "Parents": [{"Name": "Fashion"}, {"Name": "Clothing"}]}, {"Name": "Fashion", "Confidence": 99.24073791503906, "Instances": [], "Parents": []}, {"Name": "Sleeve", "Confidence": 99.20700073242188, "Instances": [], "Parents": [{"Name": "Clothing"}]}, {"Name": "Long Sleeve", "Confidence": 96.98526000976562, "Instances": [], "Parents": [{"Name": "Sleeve"}, {"Name": "Clothing"}]}, {"Name": "Person", "Confidence": 89.90956115722656, "Instances": [{"BoundingBox": {"Width": 0.863981306552887, "Height": 0.9481987953186035, "Left": 0.07913538813591003, "Top": 0.0160687193274498}, "Confidence": 89.90956115722656}], "Parents": []}, {"Name": "Female", "Confidence": 87.94175720214844, "Instances": [], "Parents": [{"Name": "Person"}]}, {"Name": "Sweater", "Confidence": 87.3312759399414, "Instances": [{"BoundingBox": {"Width": 0.799350380897522, "Height": 0.8042945861816406, "Left": 0.12870202958583832, "Top": 0.11215020716190338}, "Confidence": 87.3312759399414}], "Parents": [{"Name": "Clothing"}]}]