[{"Name": "Clothing", "Confidence": 99.9239730834961, "Instances": [], "Parents": []}, {"Name": "Apparel", "Confidence": 99.9239730834961, "Instances": [], "Parents": []}, {"Name": "Person", "Confidence": 99.54493713378906, "Instances": [{"BoundingBox": {"Width": 0.23816388845443726, "Height": 0.46979257464408875, "Left": 0.130132257938385, "Top": 0.4529685080051422}, "Confidence": 99.54493713378906}, {"BoundingBox": {"Width": 0.2051965445280075, "Height": 0.4796171188354492, "Left": 0.4553321897983551, "Top": 0.4538551867008209}, "Confidence": 99.1925048828125}, {"BoundingBox": {"Width": 0.16916637122631073, "Height": 0.24245388805866241, "Left": 0.3123798966407776, "Top": 0.6808830499649048}, "Confidence": 99.01106262207031}], "Parents": []}, {"Name": "Jacket", "Confidence": 98.11980438232422, "Instances": [{"BoundingBox": {"Width": 0.21809637546539307, "Height": 0.23612673580646515, "Left": 0.13435815274715424, "Top": 0.4743841886520386}, "Confidence": 98.11980438232422}], "Parents": [{"Name": "Coat"}, {"Name": "Clothing"}]}, {"Name": "Coat", "Confidence": 98.11980438232422, "Instances": [], "Parents": [{"Name": "Clothing"}]}, {"Name": "Pants", "Confidence": 95.66765594482422, "Instances": [], "Parents": [{"Name": "Clothing"}]}, {"Name": "Pedestrian", "Confidence": 89.06025695800781, "Instances": [], "Parents": [{"Name": "Person"}]}, {"Name": "Shoe", "Confidence": 86.78627014160156, "Instances": [{"BoundingBox": {"Width": 0.08120905607938766, "Height": 0.06362508237361908, "Left": 0.5651763677597046, "Top": 0.8772903084754944}, "Confidence": 86.78627014160156}, {"BoundingBox": {"Width": 0.0957048237323761, "Height": 0.0537889264523983, "Left": 0.4993782341480255, "Top": 0.8721676468849182}, "Confidence": 78.73690795898438}, {"BoundingBox": {"Width": 0.07875217497348785, "Height": 0.06503160297870636, "Left": 0.178640216588974, "Top": 0.8638456463813782}, "Confidence": 57.91529083251953}], "Parents": [{"Name": "Footwear"}, {"Name": "Clothing"}]}, {"Name": "Footwear", "Confidence": 86.78627014160156, "Instances": [], "Parents": [{"Name": "Clothing"}]}, {"Name": "Jeans", "Confidence": 82.5553970336914, "Instances": [], "Parents": [{"Name": "Pants"}, {"Name": "Clothing"}]}]