[{"Name": "Face", "Confidence": 99.9737777709961, "Instances": [], "Parents": [{"Name": "Person"}]}, {"Name": "Person", "Confidence": 99.9737777709961, "Instances": [{"BoundingBox": {"Width": 0.7315427660942078, "Height": 0.9078488349914551, "Left": 0.04620148986577988, "Top": 0.05957288667559624}, "Confidence": 75.34197235107422}], "Parents": []}, {"Name": "Human", "Confidence": 99.9737777709961, "Instances": [], "Parents": []}, {"Name": "Female", "Confidence": 86.46177673339844, "Instances": [], "Parents": [{"Name": "Person"}]}]