[{"Name": "Clothing", "Confidence": 99.95431518554688, "Instances": [], "Parents": []}, {"Name": "Apparel", "Confidence": 99.95431518554688, "Instances": [], "Parents": []}, {"Name": "Person", "Confidence": 99.47723388671875, "Instances": [{"BoundingBox": {"Width": 0.4635170102119446, "Height": 0.8194513320922852, "Left": 0.011487841606140137, "Top": 0.16529631614685059}, "Confidence": 99.47723388671875}, {"BoundingBox": {"Width": 0.5668312907218933, "Height": 0.8015956878662109, "Left": 0.420710951089859, "Top": 0.19684186577796936}, "Confidence": 99.20443725585938}], "Parents": []}, {"Name": "Human", "Confidence": 99.47723388671875, "Instances": [], "Parents": []}, {"Name": "Bonnet", "Confidence": 91.54426574707031, "Instances": [], "Parents": [{"Name": "Hat"}, {"Name": "Clothing"}]}, {"Name": "Hat", "Confidence": 91.54426574707031, "Instances": [], "Parents": [{"Name": "Clothing"}]}]