[{"Name": "Person", "Confidence": 99.52560424804688, "Instances": [{"BoundingBox": {"Width": 0.2593270242214203, "Height": 0.2690856456756592, "Left": 0.4064387083053589, "Top": 0.6042617559432983}, "Confidence": 99.52560424804688}, {"BoundingBox": {"Width": 0.2072470784187317, "Height": 0.3709931969642639, "Left": 0.7387716770172119, "Top": 0.49800702929496765}, "Confidence": 79.35819244384766}], "Parents": []}, {"Name": "Human", "Confidence": 99.52560424804688, "Instances": [], "Parents": []}, {"Name": "Text", "Confidence": 99.19222259521484, "Instances": [], "Parents": []}, {"Name": "Newspaper", "Confidence": 98.73771667480469, "Instances": [], "Parents": [{"Name": "Text"}]}]