[{"Name": "Cream", "Confidence": 99.68585968017578, "Instances": [], "Parents": [{"Name": "Dessert"}, {"Name": "Food"}]}, {"Name": "Dessert", "Confidence": 99.68585968017578, "Instances": [], "Parents": [{"Name": "Food"}]}, {"Name": "Food", "Confidence": 99.68585968017578, "Instances": [], "Parents": []}, {"Name": "Person", "Confidence": 98.63433837890625, "Instances": [{"BoundingBox": {"Width": 0.8421875238418579, "Height": 0.9622997641563416, "Left": 0.1564236581325531, "Top": 0.00734275346621871}, "Confidence": 98.63433837890625}], "Parents": []}, {"Name": "Ice Cream", "Confidence": 97.07217407226562, "Instances": [], "Parents": [{"Name": "Cream"}, {"Name": "Dessert"}, {"Name": "Food"}]}, {"Name": "Face", "Confidence": 92.37286376953125, "Instances": [], "Parents": [{"Name": "Person"}]}, {"Name": "Tie", "Confidence": 88.2177505493164, "Instances": [{"BoundingBox": {"Width": 0.2447860985994339, "Height": 0.4758014678955078, "Left": 0.32939356565475464, "Top": 0.518272340297699}, "Confidence": 88.2177505493164}], "Parents": [{"Name": "Accessories"}]}, {"Name": "Accessories", "Confidence": 88.2177505493164, "Instances": [], "Parents": []}, {"Name": "Icing", "Confidence": 84.20350646972656, "Instances": [], "Parents": [{"Name": "Cream"}, {"Name": "Cake"}, {"Name": "Dessert"}, {"Name": "Food"}]}, {"Name": "Cake", "Confidence": 84.20350646972656, "Instances": [], "Parents": [{"Name": "Dessert"}, {"Name": "Food"}]}]