[{"Name": "Nature", "Confidence": 99.68870544433594, "Instances": [], "Parents": []}, {"Name": "Outdoors", "Confidence": 99.50919342041016, "Instances": [], "Parents": []}, {"Name": "Night", "Confidence": 95.520751953125, "Instances": [], "Parents": [{"Name": "Outdoors"}, {"Name": "Nature"}]}, {"Name": "Outer Space", "Confidence": 95.24911499023438, "Instances": [], "Parents": [{"Name": "Astronomy"}]}, {"Name": "Universe", "Confidence": 95.24911499023438, "Instances": [], "Parents": [{"Name": "Astronomy"}]}, {"Name": "Space", "Confidence": 95.24911499023438, "Instances": [], "Parents": [{"Name": "Astronomy"}]}, {"Name": "Astronomy", "Confidence": 95.24911499023438, "Instances": [], "Parents": []}, {"Name": "Moon", "Confidence": 90.61115264892578, "Instances": [], "Parents": [{"Name": "Outer Space"}, {"Name": "Night"}, {"Name": "Astronomy"}, {"Name": "Outdoors"}, {"Name": "Nature"}]}]