[{"Name": "Person", "Confidence": 99.72235107421875, "Instances": [{"BoundingBox": {"Width": 0.12946946918964386, "Height": 0.36804717779159546, "Left": 0.8698360919952393, "Top": 0.30333465337753296}, "Confidence": 99.72235107421875}, {"BoundingBox": {"Width": 0.735228419303894, "Height": 0.9522229433059692, "Left": 0.10800781100988388, "Top": 0.03433765470981598}, "Confidence": 98.63842010498047}], "Parents": []}, {"Name": "Human", "Confidence": 99.72235107421875, "Instances": [], "Parents": []}, {"Name": "Shoe", "Confidence": 99.41996765136719, "Instances": [{"BoundingBox": {"Width": 0.18732893466949463, "Height": 0.08815566450357437, "Left": 0.4547262489795685, "Top": 0.907829761505127}, "Confidence": 99.41996765136719}, {"BoundingBox": {"Width": 0.12819011509418488, "Height": 0.14629776775836945, "Left": 0.12051000446081161, "Top": 0.8229261040687561}, "Confidence": 91.02117919921875}, {"BoundingBox": {"Width": 0.07679986208677292, "Height": 0.03210713714361191, "Left": 0.9040824174880981, "Top": 0.6378287672996521}, "Confidence": 68.3622817993164}], "Parents": [{"Name": "Footwear"}, {"Name": "Clothing"}]}, {"Name": "Clothing", "Confidence": 99.41996765136719, "Instances": [], "Parents": []}, {"Name": "Footwear", "Confidence": 99.41996765136719, "Instances": [], "Parents": [{"Name": "Clothing"}]}, {"Name": "Working Out", "Confidence": 97.47598266601562, "Instances": [], "Parents": [{"Name": "Sport"}, {"Name": "Person"}]}, {"Name": "Sport", "Confidence": 97.47598266601562, "Instances": [], "Parents": [{"Name": "Person"}]}, {"Name": "Fitness", "Confidence": 97.31670379638672, "Instances": [], "Parents": [{"Name": "Working Out"}, {"Name": "Sport"}, {"Name": "Person"}]}, {"Name": "Gym", "Confidence": 91.32611083984375, "Instances": [], "Parents": [{"Name": "Fitness"}, {"Name": "Working Out"}, {"Name": "Sport"}, {"Name": "Person"}]}, {"Name": "Shorts", "Confidence": 80.5181655883789, "Instances": [], "Parents": [{"Name": "Clothing"}]}]