[{"Name": "Flyer", "Confidence": 99.88939666748047, "Instances": [], "Parents": [{"Name": "Poster"}, {"Name": "Paper"}, {"Name": "Advertisement"}]}, {"Name": "Brochure", "Confidence": 99.88939666748047, "Instances": [], "Parents": [{"Name": "Poster"}, {"Name": "Paper"}, {"Name": "Advertisement"}]}, {"Name": "Poster", "Confidence": 99.88939666748047, "Instances": [], "Parents": [{"Name": "Advertisement"}]}, {"Name": "Advertisement", "Confidence": 99.88939666748047, "Instances": [], "Parents": []}, {"Name": "Paper", "Confidence": 99.88939666748047, "Instances": [], "Parents": []}, {"Name": "Bus", "Confidence": 98.9406509399414, "Instances": [{"BoundingBox": {"Width": 0.1987113058567047, "Height": 0.1551436185836792, "Left": 0.2535712420940399, "Top": 0.723284125328064}, "Confidence": 98.9406509399414}, {"BoundingBox": {"Width": 0.2607828974723816, "Height": 0.182031512260437, "Left": 0.43833333253860474, "Top": 0.7019945383071899}, "Confidence": 97.13666534423828}], "Parents": [{"Name": "Vehicle"}, {"Name": "Transportation"}]}, {"Name": "Transportation", "Confidence": 98.9406509399414, "Instances": [], "Parents": []}, {"Name": "Vehicle", "Confidence": 98.9406509399414, "Instances": [], "Parents": [{"Name": "Transportation"}]}, {"Name": "Car", "Confidence": 97.76226043701172, "Instances": [{"BoundingBox": {"Width": 0.22466345131397247, "Height": 0.1117631122469902, "Left": 0.6786442399024963, "Top": 0.7868937849998474}, "Confidence": 97.76226043701172}, {"BoundingBox": {"Width": 0.12909282743930817, "Height": 0.09815976023674011, "Left": 0.13257484138011932, "Top": 0.7716042995452881}, "Confidence": 96.95661926269531}], "Parents": [{"Name": "Vehicle"}, {"Name": "Transportation"}]}, {"Name": "Automobile", "Confidence": 97.76226043701172, "Instances": [], "Parents": [{"Name": "Vehicle"}, {"Name": "Transportation"}]}]