[{"Name": "Person", "Confidence": 98.7959213256836, "Instances": [{"BoundingBox": {"Width": 0.42358770966529846, "Height": 0.33166003227233887, "Left": 0.32701417803764343, "Top": 0.5175131559371948}, "Confidence": 98.7959213256836}], "Parents": []}, {"Name": "Human", "Confidence": 98.7959213256836, "Instances": [], "Parents": []}, {"Name": "Handrail", "Confidence": 98.5970458984375, "Instances": [], "Parents": []}, {"Name": "Shorts", "Confidence": 97.3254165649414, "Instances": [], "Parents": [{"Name": "Clothing"}]}, {"Name": "Clothing", "Confidence": 97.3254165649414, "Instances": [], "Parents": []}, {"Name": "Wood", "Confidence": 97.17184448242188, "Instances": [], "Parents": []}, {"Name": "Flooring", "Confidence": 96.54991149902344, "Instances": [], "Parents": [{"Name": "Person"}]}, {"Name": "Railing", "Confidence": 94.89144897460938, "Instances": [], "Parents": []}, {"Name": "Hardwood", "Confidence": 85.7770004272461, "Instances": [], "Parents": [{"Name": "Wood"}]}, {"Name": "Floor", "Confidence": 82.962646484375, "Instances": [], "Parents": []}]