[{"Name": "Person", "Confidence": 98.67597198486328, "Instances": [{"BoundingBox": {"Width": 0.9768624901771545, "Height": 0.7636306881904602, "Left": 0.022218311205506325, "Top": 0.18578431010246277}, "Confidence": 98.67597198486328}], "Parents": []}, {"Name": "Human", "Confidence": 98.67597198486328, "Instances": [], "Parents": []}, {"Name": "Helmet", "Confidence": 97.71406555175781, "Instances": [{"BoundingBox": {"Width": 0.9015865921974182, "Height": 0.47855904698371887, "Left": 0.04807354509830475, "Top": 0.08710427582263947}, "Confidence": 97.71406555175781}], "Parents": [{"Name": "Clothing"}]}, {"Name": "Clothing", "Confidence": 97.71406555175781, "Instances": [], "Parents": []}, {"Name": "Apparel", "Confidence": 97.71406555175781, "Instances": [], "Parents": []}, {"Name": "Face", "Confidence": 91.6724624633789, "Instances": [], "Parents": [{"Name": "Person"}]}, {"Name": "Head", "Confidence": 86.90396118164062, "Instances": [], "Parents": []}]