[{"Name": "Plot", "Confidence": 98.12742614746094, "Instances": [], "Parents": []}, {"Name": "Menu", "Confidence": 97.44463348388672, "Instances": [{"BoundingBox": {"Width": 0.9064821600914001, "Height": 0.7695606350898743, "Left": 0.0380033515393734, "Top": 0.12953495979309082}, "Confidence": 97.44463348388672}], "Parents": [{"Name": "Text"}]}, {"Name": "Text", "Confidence": 97.44463348388672, "Instances": [], "Parents": []}, {"Name": "Diagram", "Confidence": 91.73529052734375, "Instances": [], "Parents": []}, {"Name": "Word", "Confidence": 83.6744613647461, "Instances": [], "Parents": []}, {"Name": "Measurements", "Confidence": 82.98473358154297, "Instances": [], "Parents": [{"Name": "Plot"}, {"Name": "Diagram"}]}]