[{"Name": "Person", "Confidence": 99.33548736572266, "Instances": [{"BoundingBox": {"Width": 0.6424502730369568, "Height": 0.7746427655220032, "Left": 0.09763253480195999, "Top": 0.20227305591106415}, "Confidence": 99.33548736572266}], "Parents": []}, {"Name": "Human", "Confidence": 99.33548736572266, "Instances": [], "Parents": []}, {"Name": "Mobile Phone", "Confidence": 95.14118194580078, "Instances": [{"BoundingBox": {"Width": 0.11174704134464264, "Height": 0.10890571027994156, "Left": 0.10550247132778168, "Top": 0.6476694345474243}, "Confidence": 95.14118194580078}], "Parents": [{"Name": "Phone"}, {"Name": "Electronics"}]}, {"Name": "Electronics", "Confidence": 95.14118194580078, "Instances": [], "Parents": []}, {"Name": "Phone", "Confidence": 95.14118194580078, "Instances": [], "Parents": [{"Name": "Electronics"}]}, {"Name": "Cell Phone", "Confidence": 95.14118194580078, "Instances": [], "Parents": [{"Name": "Phone"}, {"Name": "Electronics"}]}, {"Name": "Clothing", "Confidence": 91.34400177001953, "Instances": [], "Parents": []}, {"Name": "Apparel", "Confidence": 91.34400177001953, "Instances": [], "Parents": []}]