[{"Name": "Cushion", "Confidence": 98.44805908203125, "Instances": [], "Parents": []}, {"Name": "Belt", "Confidence": 98.25921630859375, "Instances": [], "Parents": [{"Name": "Accessories"}]}, {"Name": "Accessories", "Confidence": 98.25921630859375, "Instances": [], "Parents": []}, {"Name": "Accessory", "Confidence": 98.25921630859375, "Instances": [], "Parents": []}, {"Name": "Person", "Confidence": 98.04650115966797, "Instances": [{"BoundingBox": {"Width": 0.8354859948158264, "Height": 0.6412590742111206, "Left": 0.08009368181228638, "Top": 0.33951258659362793}, "Confidence": 98.04650115966797}], "Parents": []}, {"Name": "Human", "Confidence": 98.04650115966797, "Instances": [], "Parents": []}, {"Name": "Seat Belt", "Confidence": 86.9766845703125, "Instances": [], "Parents": [{"Name": "Belt"}, {"Name": "Accessories"}]}]