[{"Name": "Cat", "Confidence": 97.61975860595703, "Instances": [{"BoundingBox": {"Width": 0.9641175866127014, "Height": 0.8924140334129333, "Left": 0.029567083343863487, "Top": 0.006072517484426498}, "Confidence": 97.61975860595703}], "Parents": [{"Name": "Pet"}, {"Name": "Mammal"}, {"Name": "Animal"}]}, {"Name": "Animal", "Confidence": 97.61975860595703, "Instances": [], "Parents": []}, {"Name": "Mammal", "Confidence": 97.61975860595703, "Instances": [], "Parents": [{"Name": "Animal"}]}, {"Name": "Pet", "Confidence": 97.61975860595703, "Instances": [], "Parents": [{"Name": "Animal"}]}, {"Name": "Mouth", "Confidence": 84.11039733886719, "Instances": [], "Parents": []}, {"Name": "Lip", "Confidence": 84.11039733886719, "Instances": [], "Parents": []}]