[{"Name": "Clothing", "Confidence": 99.70668029785156, "Instances": [], "Parents": []}, {"Name": "Person", "Confidence": 99.3058090209961, "Instances": [{"BoundingBox": {"Width": 0.493452250957489, "Height": 0.4888388514518738, "Left": 0.4976634085178375, "Top": 0.5028033256530762}, "Confidence": 99.3058090209961}], "Parents": []}, {"Name": "Outdoors", "Confidence": 95.24410247802734, "Instances": [], "Parents": []}, {"Name": "Nature", "Confidence": 95.10326385498047, "Instances": [], "Parents": []}, {"Name": "Shoreline", "Confidence": 89.34827423095703, "Instances": [], "Parents": [{"Name": "Water"}]}, {"Name": "Water", "Confidence": 89.34827423095703, "Instances": [], "Parents": []}, {"Name": "Sleeve", "Confidence": 87.75825500488281, "Instances": [], "Parents": [{"Name": "Clothing"}]}, {"Name": "Sea", "Confidence": 87.08911895751953, "Instances": [], "Parents": [{"Name": "Outdoors"}, {"Name": "Water"}, {"Name": "Nature"}]}, {"Name": "Beach", "Confidence": 82.95226287841797, "Instances": [], "Parents": [{"Name": "Coast"}, {"Name": "Shoreline"}, {"Name": "Sea"}, {"Name": "Water"}, {"Name": "Outdoors"}, {"Name": "Nature"}]}, {"Name": "Coast", "Confidence": 82.95226287841797, "Instances": [], "Parents": [{"Name": "Shoreline"}, {"Name": "Sea"}, {"Name": "Water"}, {"Name": "Outdoors"}, {"Name": "Nature"}]}]