[{"Name": "Clothing", "Confidence": 99.70265197753906, "Instances": [], "Parents": []}, {"Name": "Apparel", "Confidence": 99.70265197753906, "Instances": [], "Parents": []}, {"Name": "Jacket", "Confidence": 96.58273315429688, "Instances": [], "Parents": [{"Name": "Coat"}, {"Name": "Clothing"}]}, {"Name": "Coat", "Confidence": 96.58273315429688, "Instances": [], "Parents": [{"Name": "Clothing"}]}, {"Name": "Person", "Confidence": 94.59693908691406, "Instances": [{"BoundingBox": {"Width": 0.7417536377906799, "Height": 0.7101122736930847, "Left": 0.04467726871371269, "Top": 0.28545230627059937}, "Confidence": 93.53047943115234}, {"BoundingBox": {"Width": 0.237600639462471, "Height": 0.6045874953269958, "Left": 0.0034003364853560925, "Top": 0.3686397671699524}, "Confidence": 82.5461196899414}], "Parents": []}, {"Name": "Human", "Confidence": 94.59693908691406, "Instances": [], "Parents": []}, {"Name": "Female", "Confidence": 92.37947082519531, "Instances": [], "Parents": [{"Name": "Person"}]}, {"Name": "Face", "Confidence": 88.79668426513672, "Instances": [], "Parents": [{"Name": "Person"}]}, {"Name": "Sleeve", "Confidence": 86.72575378417969, "Instances": [], "Parents": [{"Name": "Clothing"}]}]