[{"Name": "Clothing", "Confidence": 99.9630126953125, "Instances": [], "Parents": []}, {"Name": "Apparel", "Confidence": 99.9630126953125, "Instances": [], "Parents": []}, {"Name": "Person", "Confidence": 94.06013488769531, "Instances": [{"BoundingBox": {"Width": 0.5446352362632751, "Height": 0.7384058833122253, "Left": 0.24748095870018005, "Top": 0.2410736382007599}, "Confidence": 94.06013488769531}], "Parents": []}, {"Name": "Human", "Confidence": 94.06013488769531, "Instances": [], "Parents": []}, {"Name": "Fashion", "Confidence": 89.22541809082031, "Instances": [], "Parents": []}]