[{"Name": "Couch", "Confidence": 99.8965835571289, "Instances": [{"BoundingBox": {"Width": 0.8875832557678223, "Height": 0.5374594330787659, "Left": 0.04616771265864372, "Top": 0.45541539788246155}, "Confidence": 76.97486114501953}], "Parents": [{"Name": "Furniture"}]}, {"Name": "Furniture", "Confidence": 99.8965835571289, "Instances": [], "Parents": []}, {"Name": "Sitting", "Confidence": 99.80291748046875, "Instances": [], "Parents": [{"Name": "Person"}]}, {"Name": "Person", "Confidence": 99.80291748046875, "Instances": [{"BoundingBox": {"Width": 0.3780877888202667, "Height": 0.7573075890541077, "Left": 0.375536173582077, "Top": 0.19746644794940948}, "Confidence": 99.23310852050781}], "Parents": []}, {"Name": "Home Decor", "Confidence": 89.546142578125, "Instances": [], "Parents": []}, {"Name": "Living Room", "Confidence": 87.16958618164062, "Instances": [], "Parents": [{"Name": "Room"}, {"Name": "Indoors"}]}, {"Name": "Indoors", "Confidence": 87.16958618164062, "Instances": [], "Parents": []}, {"Name": "Room", "Confidence": 87.16958618164062, "Instances": [], "Parents": [{"Name": "Indoors"}]}, {"Name": "Wood", "Confidence": 84.37271881103516, "Instances": [], "Parents": []}, {"Name": "Chair", "Confidence": 81.42134094238281, "Instances": [{"BoundingBox": {"Width": 0.3483787477016449, "Height": 0.2112739533185959, "Left": 0.6509268283843994, "Top": 0.7880315780639648}, "Confidence": 81.42134094238281}, {"BoundingBox": {"Width": 0.3989042639732361, "Height": 0.4932432472705841, "Left": 0.5652107000350952, "Top": 0.4921775758266449}, "Confidence": 78.37531280517578}], "Parents": [{"Name": "Furniture"}]}]