[{"Name": "Clothing", "Confidence": 96.20634460449219, "Instances": [], "Parents": []}, {"Name": "Apparel", "Confidence": 96.20634460449219, "Instances": [], "Parents": []}, {"Name": "Person", "Confidence": 93.68726348876953, "Instances": [{"BoundingBox": {"Width": 0.3276839256286621, "Height": 0.5489914417266846, "Left": 0.3715136647224426, "Top": 0.4481065571308136}, "Confidence": 93.15906524658203}], "Parents": []}, {"Name": "Human", "Confidence": 93.68726348876953, "Instances": [], "Parents": []}, {"Name": "Skating", "Confidence": 91.8670425415039, "Instances": [], "Parents": [{"Name": "Sport"}, {"Name": "Person"}]}, {"Name": "Sport", "Confidence": 91.8670425415039, "Instances": [], "Parents": [{"Name": "Person"}]}, {"Name": "Sports", "Confidence": 91.8670425415039, "Instances": [], "Parents": [{"Name": "Person"}]}, {"Name": "Ice Skating", "Confidence": 91.08920288085938, "Instances": [], "Parents": [{"Name": "Skating"}, {"Name": "Sport"}, {"Name": "Person"}]}]