[{"Name": "Sweets", "Confidence": 98.33831787109375, "Instances": [], "Parents": [{"Name": "Food"}]}, {"Name": "Food", "Confidence": 98.33831787109375, "Instances": [], "Parents": []}, {"Name": "Spoon", "Confidence": 96.67620086669922, "Instances": [{"BoundingBox": {"Width": 0.5775546431541443, "Height": 0.35570043325424194, "Left": 0.0008340835338458419, "Top": 0.6411745548248291}, "Confidence": 96.67620086669922}], "Parents": [{"Name": "Cutlery"}]}, {"Name": "Cutlery", "Confidence": 96.67620086669922, "Instances": [], "Parents": []}, {"Name": "Meal", "Confidence": 96.4766845703125, "Instances": [], "Parents": [{"Name": "Food"}]}, {"Name": "Dish", "Confidence": 94.13298034667969, "Instances": [], "Parents": [{"Name": "Meal"}, {"Name": "Food"}]}, {"Name": "Bowl", "Confidence": 89.34827423095703, "Instances": [], "Parents": []}, {"Name": "Dessert", "Confidence": 87.65522003173828, "Instances": [], "Parents": [{"Name": "Food"}]}, {"Name": "Plant", "Confidence": 83.76253509521484, "Instances": [], "Parents": []}, {"Name": "Cream", "Confidence": 80.8563461303711, "Instances": [], "Parents": [{"Name": "Dessert"}, {"Name": "Food"}]}]