[{"Name": "Clothing", "Confidence": 99.15882110595703, "Instances": [], "Parents": []}, {"Name": "Apparel", "Confidence": 99.15882110595703, "Instances": [], "Parents": []}, {"Name": "Person", "Confidence": 97.11756134033203, "Instances": [{"BoundingBox": {"Width": 0.7248251438140869, "Height": 0.9239842891693115, "Left": 0.2387869656085968, "Top": 0.02994971163570881}, "Confidence": 97.11756134033203}], "Parents": []}, {"Name": "Human", "Confidence": 97.11756134033203, "Instances": [], "Parents": []}, {"Name": "Furniture", "Confidence": 92.13471984863281, "Instances": [], "Parents": []}, {"Name": "Sweater", "Confidence": 88.96863555908203, "Instances": [], "Parents": [{"Name": "Clothing"}]}, {"Name": "Glasses", "Confidence": 87.88922882080078, "Instances": [{"BoundingBox": {"Width": 0.3348418176174164, "Height": 0.09473027288913727, "Left": 0.4590701758861542, "Top": 0.18728090822696686}, "Confidence": 87.88922882080078}], "Parents": [{"Name": "Accessories"}]}, {"Name": "Accessories", "Confidence": 87.88922882080078, "Instances": [], "Parents": []}, {"Name": "Accessory", "Confidence": 87.88922882080078, "Instances": [], "Parents": []}, {"Name": "Cushion", "Confidence": 80.40454864501953, "Instances": [], "Parents": []}]