[{"Name": "Dinner", "Confidence": 96.95995330810547, "Instances": [], "Parents": [{"Name": "Food"}]}, {"Name": "Supper", "Confidence": 96.95995330810547, "Instances": [], "Parents": [{"Name": "Food"}]}, {"Name": "Food", "Confidence": 96.95995330810547, "Instances": [], "Parents": []}, {"Name": "Meal", "Confidence": 96.3089599609375, "Instances": [], "Parents": [{"Name": "Food"}]}, {"Name": "Dish", "Confidence": 94.80916595458984, "Instances": [], "Parents": [{"Name": "Meal"}, {"Name": "Food"}]}, {"Name": "Plant", "Confidence": 86.82882690429688, "Instances": [], "Parents": []}]