[{"Name": "Lobster", "Confidence": 90.01219177246094, "Instances": [{"BoundingBox": {"Width": 0.8087376356124878, "Height": 0.6859475374221802, "Left": 0.05458822846412659, "Top": 0.2672799825668335}, "Confidence": 90.01219177246094}], "Parents": [{"Name": "Seafood"}, {"Name": "Sea Life"}, {"Name": "Food"}, {"Name": "Animal"}]}, {"Name": "Animal", "Confidence": 90.01219177246094, "Instances": [], "Parents": []}, {"Name": "Sea Life", "Confidence": 90.01219177246094, "Instances": [], "Parents": [{"Name": "Animal"}]}, {"Name": "Seafood", "Confidence": 90.01219177246094, "Instances": [], "Parents": [{"Name": "Food"}]}, {"Name": "Food", "Confidence": 90.01219177246094, "Instances": [], "Parents": []}, {"Name": "Plant", "Confidence": 84.77286529541016, "Instances": [], "Parents": []}]