[{"Name": "Bowl", "Confidence": 99.99545288085938, "Instances": [], "Parents": []}, {"Name": "Dish", "Confidence": 99.9892807006836, "Instances": [], "Parents": [{"Name": "Meal"}, {"Name": "Food"}]}, {"Name": "Meal", "Confidence": 99.9892807006836, "Instances": [], "Parents": [{"Name": "Food"}]}, {"Name": "Food", "Confidence": 99.9892807006836, "Instances": [], "Parents": []}, {"Name": "Soup Bowl", "Confidence": 96.27124786376953, "Instances": [], "Parents": [{"Name": "Bowl"}]}, {"Name": "Soup", "Confidence": 94.00408172607422, "Instances": [], "Parents": [{"Name": "Dish"}, {"Name": "Soup Bowl"}, {"Name": "Meal"}, {"Name": "Bowl"}, {"Name": "Food"}]}]