[{"Name": "Burger", "Confidence": 99.895751953125, "Instances": [{"BoundingBox": {"Width": 0.6521915793418884, "Height": 0.7714701294898987, "Left": 0.17415925860404968, "Top": 0.15196841955184937}, "Confidence": 99.895751953125}], "Parents": [{"Name": "Food"}]}, {"Name": "Food", "Confidence": 99.895751953125, "Instances": [], "Parents": []}, {"Name": "Sweets", "Confidence": 94.11988830566406, "Instances": [], "Parents": [{"Name": "Food"}]}, {"Name": "Confectionery", "Confidence": 94.11988830566406, "Instances": [], "Parents": [{"Name": "Food"}]}, {"Name": "Dessert", "Confidence": 87.43270111083984, "Instances": [], "Parents": [{"Name": "Food"}]}, {"Name": "Person", "Confidence": 82.07108306884766, "Instances": [{"BoundingBox": {"Width": 0.8586084842681885, "Height": 0.22519978880882263, "Left": 0.06270170956850052, "Top": 0.762139618396759}, "Confidence": 82.07108306884766}], "Parents": []}, {"Name": "Human", "Confidence": 82.07108306884766, "Instances": [], "Parents": []}]