[{"Name": "Plant", "Confidence": 97.74335479736328, "Instances": [], "Parents": []}, {"Name": "Strawberry", "Confidence": 95.61415100097656, "Instances": [], "Parents": [{"Name": "Fruit"}, {"Name": "Plant"}, {"Name": "Food"}]}, {"Name": "Food", "Confidence": 95.61415100097656, "Instances": [], "Parents": []}, {"Name": "Fruit", "Confidence": 95.61415100097656, "Instances": [], "Parents": [{"Name": "Plant"}, {"Name": "Food"}]}, {"Name": "Raspberry", "Confidence": 90.946533203125, "Instances": [], "Parents": [{"Name": "Fruit"}, {"Name": "Plant"}, {"Name": "Food"}]}, {"Name": "Blueberry", "Confidence": 86.05400848388672, "Instances": [], "Parents": [{"Name": "Fruit"}, {"Name": "Plant"}, {"Name": "Food"}]}]