[{"Name": "Bowl", "Confidence": 97.0639877319336, "Instances": [], "Parents": []}, {"Name": "Dish", "Confidence": 96.23048400878906, "Instances": [], "Parents": [{"Name": "Meal"}, {"Name": "Food"}]}, {"Name": "Meal", "Confidence": 96.23048400878906, "Instances": [], "Parents": [{"Name": "Food"}]}, {"Name": "Food", "Confidence": 96.23048400878906, "Instances": [], "Parents": []}, {"Name": "Plant", "Confidence": 95.38433074951172, "Instances": [], "Parents": []}, {"Name": "Lunch", "Confidence": 83.93285369873047, "Instances": [], "Parents": [{"Name": "Meal"}, {"Name": "Food"}]}, {"Name": "Produce", "Confidence": 83.81641387939453, "Instances": [], "Parents": [{"Name": "Food"}]}]