[{"Name": "Bowl", "Confidence": 98.97128295898438, "Instances": [], "Parents": []}, {"Name": "Dish", "Confidence": 98.09687042236328, "Instances": [], "Parents": [{"Name": "Meal"}]}, {"Name": "Meal", "Confidence": 98.09687042236328, "Instances": [], "Parents": []}, {"Name": "Plant", "Confidence": 97.08560180664062, "Instances": [], "Parents": []}, {"Name": "Potted Plant", "Confidence": 94.29932403564453, "Instances": [], "Parents": [{"Name": "Plant"}, {"Name": "Vase"}, {"Name": "Jar"}, {"Name": "Pottery"}]}, {"Name": "Pottery", "Confidence": 94.29932403564453, "Instances": [], "Parents": []}, {"Name": "Vase", "Confidence": 94.29932403564453, "Instances": [], "Parents": [{"Name": "Jar"}, {"Name": "Pottery"}]}, {"Name": "Jar", "Confidence": 94.29932403564453, "Instances": [], "Parents": []}, {"Name": "Egg", "Confidence": 94.09467315673828, "Instances": [{"BoundingBox": {"Width": 0.13480012118816376, "Height": 0.0756971538066864, "Left": 0.3110969662666321, "Top": 0.5809211134910583}, "Confidence": 94.09467315673828}], "Parents": []}, {"Name": "Planter", "Confidence": 80.25585174560547, "Instances": [], "Parents": [{"Name": "Potted Plant"}, {"Name": "Plant"}, {"Name": "Vase"}, {"Name": "Jar"}, {"Name": "Pottery"}]}]