[{"Name": "Noodle", "Confidence": 99.84640502929688, "Instances": [], "Parents": [{"Name": "Pasta"}, {"Name": "Food"}]}, {"Name": "Pasta", "Confidence": 99.84640502929688, "Instances": [], "Parents": [{"Name": "Food"}]}, {"Name": "Food", "Confidence": 99.84640502929688, "Instances": [], "Parents": []}, {"Name": "Dish", "Confidence": 94.41156768798828, "Instances": [], "Parents": [{"Name": "Meal"}, {"Name": "Food"}]}, {"Name": "Meal", "Confidence": 94.41156768798828, "Instances": [], "Parents": [{"Name": "Food"}]}, {"Name": "Vermicelli", "Confidence": 94.3629150390625, "Instances": [], "Parents": [{"Name": "Noodle"}, {"Name": "Pasta"}, {"Name": "Food"}]}]