[{"Name": "Plant", "Confidence": 98.78076934814453, "Instances": [], "Parents": []}, {"Name": "Food", "Confidence": 92.56763458251953, "Instances": [], "Parents": []}, {"Name": "Dessert", "Confidence": 88.34150695800781, "Instances": [], "Parents": [{"Name": "Food"}]}, {"Name": "Nut", "Confidence": 83.90582275390625, "Instances": [], "Parents": [{"Name": "Vegetable"}, {"Name": "Plant"}, {"Name": "Food"}]}, {"Name": "Vegetable", "Confidence": 83.90582275390625, "Instances": [], "Parents": [{"Name": "Plant"}, {"Name": "Food"}]}]